{"v":"5.6.6","ip":0,"op":80,"fr":60,"w":24,"h":24,"layers":[{"ind":2490,"nm":"surface8705","ao":0,"ip":0,"op":80,"st":0,"ty":4,"ks":{"ty":"tr","o":{"k":100},"r":{"k":0},"p":{"a":0,"k":[0,0,0],"ix":2},"a":{"k":[0,0]},"s":{"k":[133.33,133.33]},"sk":{"k":0},"sa":{"k":0}},"shapes":[{"ty":"gr","hd":false,"nm":"surface8705","it":[{"ty":"gr","hd":false,"it":[{"ty":"sh","ks":{"k":{"i":[[0,0],[0,0],[0.7,0],[0,0],[0.15,0.69],[0,0]],"o":[[0,0],[-0.15,0.69],[0,0],[-0.71,0],[0,0],[0,0]],"v":[[19.76,12],[18.07,19.79],[16.61,20.97],[7.4,20.97],[5.94,19.79],[4.25,12]],"c":false}}},{"ty":"st","lc":2,"lj":2,"ml":4,"o":{"k":100},"w":{"k":1.5},"c":{"k":[1,0.4902,0.302,1]},"hd":false},{"ty":"tr","o":{"k":100},"r":{"k":0},"p":{"k":[0,0]},"a":{"k":[0,0]},"s":{"k":[75,75]},"sk":{"k":0},"sa":{"k":0},"hd":false}]},{"ty":"gr","hd":false,"it":[{"ty":"sh","ks":{"k":{"i":[[0,0],[0,0]],"o":[[0,0],[0,0]],"v":[[9.96,3.03],[7,7.97]],"c":false}}},{"ty":"st","lc":2,"lj":2,"ml":4,"o":{"k":100},"w":{"k":1.5},"c":{"k":[1,0.4902,0.302,1]},"hd":false},{"ty":"tr","o":{"k":100},"r":{"k":0},"p":{"k":[0,0]},"a":{"k":[0,0]},"s":{"k":[75,75]},"sk":{"k":0},"sa":{"k":0},"hd":false}]},{"ty":"gr","hd":false,"it":[{"ty":"sh","ks":{"k":{"i":[[0,0],[0,0]],"o":[[0,0],[0,0]],"v":[[14.04,3.03],[17,7.97]],"c":false}}},{"ty":"st","lc":2,"lj":2,"ml":4,"o":{"k":100},"w":{"k":1.5},"c":{"k":[1,0.4902,0.302,1]},"hd":false},{"ty":"tr","o":{"k":100},"r":{"k":0},"p":{"k":[0,0]},"a":{"k":[0,0]},"s":{"k":[75,75]},"sk":{"k":0},"sa":{"k":0},"hd":false}]},{"ty":"gr","hd":false,"it":[{"ty":"sh","ks":{"k":{"i":[[0,0],[0,0],[0,0.55],[0,0],[-0.55,0],[0,0],[0,-0.55],[0,0],[0.55,0]],"o":[[0,0],[-0.55,0],[0,0],[0,-0.55],[0,0],[0.55,0],[0,0],[0,0.55],[0,0]],"v":[[20,12],[4,12],[3,11],[3,9],[4,8],[20,8],[21,9],[21,11],[20,12]],"c":true}}},{"ty":"st","lc":2,"lj":2,"ml":4,"o":{"k":100},"w":{"k":1.5},"c":{"k":[1,0.4902,0.302,1]},"hd":false},{"ty":"tr","o":{"k":100},"r":{"k":0},"p":{"k":[0,0]},"a":{"k":[0,0]},"s":{"k":[75,75]},"sk":{"k":0},"sa":{"k":0},"hd":false}]},{"ty":"gr","hd":false,"it":[{"ty":"sh","ks":{"k":{"i":[[0,0],[0,0]],"o":[[0,0],[0,0]],"v":[[10,15.98],[10,16.99]],"c":false}}},{"ty":"st","lc":2,"lj":2,"ml":4,"o":{"k":100},"w":{"k":1.5},"c":{"k":[1,0.4902,0.302,1]},"hd":false},{"ty":"tr","o":{"k":100},"r":{"k":0},"p":{"k":[0,0]},"a":{"k":[0,0]},"s":{"k":[75,75]},"sk":{"k":0},"sa":{"k":0},"hd":false}]},{"ty":"gr","hd":false,"it":[{"ty":"sh","ks":{"k":{"i":[[0,0],[0,0]],"o":[[0,0],[0,0]],"v":[[14,15.98],[14,16.99]],"c":false}}},{"ty":"st","lc":2,"lj":2,"ml":4,"o":{"k":100},"w":{"k":1.5},"c":{"k":[1,0.4902,0.302,1]},"hd":false},{"ty":"tr","o":{"k":100},"r":{"k":0},"p":{"k":[0,0]},"a":{"k":[0,0]},"s":{"k":[75,75]},"sk":{"k":0},"sa":{"k":0},"hd":false}]},{"ty":"tr","o":{"k":100},"r":{"k":0},"p":{"k":[0,0]},"a":{"k":[0,0]},"s":{"k":[100,100]},"sk":{"k":0},"sa":{"k":0},"hd":false}]},{"ty":"tm","s":{"a":0,"k":0,"ix":1},"e":{"a":1,"k":[{"i":{"x":[0.35],"y":[1]},"o":{"x":[0.17],"y":[0.17]},"t":0,"s":[25]},{"t":55,"s":[100]}],"ix":2},"o":{"a":0,"k":0,"ix":3},"m":1,"ix":2,"nm":"Trim Paths 1","mn":"ADBE Vector Filter - Trim","hd":false}]}],"meta":{"g":"LF SVG to Lottie"}}